phonk/__init__.py
phonk/rhymescore.py
phonk/data/create_diffs.py
phonk/data/diffs.csv
phonk/data/hayes.csv
phonk-0.0.3.dist-info/LICENSE.md
phonk-0.0.3.dist-info/METADATA
phonk-0.0.3.dist-info/WHEEL
phonk-0.0.3.dist-info/top_level.txt
phonk-0.0.3.dist-info/RECORD
