Metadata-Version: 2.1
Name: phonk
Version: 0.0.3
Summary: Some helpful phonetics and phonology functions
Home-page: https://github.com/nickdanis/phonk
Author: Nick Danis
Author-email: nsdanis@wustl.edu
License: UNKNOWN
Project-URL: Bug Tracker, https://github.com/nickdanis/phonk/issues
Platform: UNKNOWN
Classifier: Programming Language :: Python :: 3
Classifier: License :: OSI Approved :: MIT License
Classifier: Operating System :: OS Independent
Requires-Python: >=3.6
License-File: LICENSE.md
